anyflow/__init__.py
anyflow/ctx.py
anyflow/err.py
anyflow/flow.py
anyflow-0.2.0.dist-info/LICENSE
anyflow-0.2.0.dist-info/WHEEL
anyflow-0.2.0.dist-info/METADATA
anyflow-0.2.0.dist-info/RECORD
